{
  "hash": "39d76b0a",
  "configHash": "718a0244",
  "lockfileHash": "773251b2",
  "browserHash": "423b1c9d",
  "optimized": {
    "vue": {
      "src": "../../../../node_modules/vue/dist/vue.runtime.esm-bundler.js",
      "file": "vue.js",
      "fileHash": "c0dfd9f6",
      "needsInterop": false
    },
    "vitepress > @vue/devtools-api": {
      "src": "../../../../node_modules/@vue/devtools-api/dist/index.js",
      "file": "vitepress___@vue_devtools-api.js",
      "fileHash": "55c0df30",
      "needsInterop": false
    },
    "vitepress > @vueuse/core": {
      "src": "../../../../node_modules/@vueuse/core/index.mjs",
      "file": "vitepress___@vueuse_core.js",
      "fileHash": "6f3f8cce",
      "needsInterop": false
    }
  },
  "chunks": {
    "chunk-DDXJJ377": {
      "file": "chunk-DDXJJ377.js"
    }
  }
}